main.py
rhino_script.py
reer_rhino_mcp-0.1.10.dist-info/licenses/LICENSE
rhino_mcp/__init__.py
rhino_mcp/rhino_tools.py
rhino_mcp/server.py
rhino_mcp/server_sse.py
rhino_mcp/web_server.py
rhino_mcp/resources/rhino_script_categories.py
reer_rhino_mcp-0.1.10.dist-info/METADATA
reer_rhino_mcp-0.1.10.dist-info/WHEEL
reer_rhino_mcp-0.1.10.dist-info/entry_points.txt
reer_rhino_mcp-0.1.10.dist-info/top_level.txt
reer_rhino_mcp-0.1.10.dist-info/RECORD
