Metadata-Version: 2.4
Name: reer-rhino-mcp
Version: 0.1.10
Summary: Rhino MCP Server
Author: REER Rhino MCP Team
License: MIT
Classifier: Programming Language :: Python :: 3
Classifier: License :: OSI Approved :: MIT License
Classifier: Operating System :: OS Independent
Requires-Python: >=3.10
License-File: LICENSE
Requires-Dist: mcp[cli]>=1.3.0
Requires-Dist: fastapi>=0.95.0
Requires-Dist: uvicorn>=0.21.0
Requires-Dist: pillow>=9.4.0
Requires-Dist: requests>=2.28.0
Requires-Dist: python-dotenv>=0.21.0
Requires-Dist: starlette>=0.27.0
Requires-Dist: httpx>=0.24.0
Requires-Dist: anyio<4.0.0,>=3.0.0
Dynamic: license-file
